lolicon_api/__init__.py
lolicon_api/module.py
lolicon_api-1.0.0.dist-info/LICENSE
lolicon_api-1.0.0.dist-info/METADATA
lolicon_api-1.0.0.dist-info/WHEEL
lolicon_api-1.0.0.dist-info/RECORD
