Metadata-Version: 2.3
Name: lolicon-api
Version: 1.0.0
Summary: A API library that allow you requests lolicon api easier
License: MIT
Author: Yang
Author-email: yang_qwq@qq.com
Requires-Python: >=3.9
Classifier: License :: OSI Approved :: MIT License
Classifier: Programming Language :: Python :: 3
Classifier: Programming Language :: Python :: 3.9
Classifier: Programming Language :: Python :: 3.10
Classifier: Programming Language :: Python :: 3.11
Classifier: Programming Language :: Python :: 3.12
Classifier: Programming Language :: Python :: 3.13
Requires-Dist: requests (>=2.32.4)
